bagpipes/__init__.py
bagpipes/config.py
bagpipes/utils.py
bagpipes/catalogue/__init__.py
bagpipes/catalogue/fit_catalogue.py
bagpipes/filters/UVJ.filt_list
bagpipes/filters/__init__.py
bagpipes/filters/filter_set.py
bagpipes/filters/UVJ/Generic-Bessell.U.dat
bagpipes/filters/UVJ/Generic-Bessell.V.dat
bagpipes/filters/UVJ/Keck-NIRC2.J.dat
bagpipes/fitting/__init__.py
bagpipes/fitting/calibration.py
bagpipes/fitting/check_priors.py
bagpipes/fitting/fit.py
bagpipes/fitting/fitted_model.py
bagpipes/fitting/noise.py
bagpipes/fitting/posterior.py
bagpipes/fitting/prior.py
bagpipes/input/__init__.py
bagpipes/input/galaxy.py
bagpipes/input/spectral_indices.py
bagpipes/models/__init__.py
bagpipes/models/agn_model.py
bagpipes/models/chemical_enrichment_history.py
bagpipes/models/dla_model.py
bagpipes/models/dust_attenuation_model.py
bagpipes/models/dust_emission_model.py
bagpipes/models/igm_model.py
bagpipes/models/model_galaxy.py
bagpipes/models/nebular_model.py
bagpipes/models/star_formation_history.py
bagpipes/models/stellar_model.py
bagpipes/models/grids/bc03_miles_nebular_cont_grids_extended_logU_nograins_cloudy25.fits
bagpipes/models/grids/bc03_miles_nebular_line_grids_extended_logU_nograins_cloudy25.fits
bagpipes/models/grids/bc03_miles_stellar_grids.fits
bagpipes/models/grids/cloudy_lines.txt
bagpipes/models/grids/cloudy_linewavs.txt
bagpipes/models/grids/dl07_grids_umin_only_no_norm.fits
bagpipes/models/grids/dl07_grids_umin_umax_no_norm.fits
bagpipes/models/grids/lyman_series_coefs_inoue_2014_table2.txt
bagpipes/models/making/__init__.py
bagpipes/models/making/igm_inoue2014.py
bagpipes/models/making/make_cloudy_models.py
bagpipes/models/making/make_draine_li_grids.py
bagpipes/plotting/__init__.py
bagpipes/plotting/general.py
bagpipes/plotting/plot_1d_posterior.py
bagpipes/plotting/plot_calibration.py
bagpipes/plotting/plot_corner.py
bagpipes/plotting/plot_galaxy.py
bagpipes/plotting/plot_model_galaxy.py
bagpipes/plotting/plot_sfh.py
bagpipes-1.3.4.dist-info/licenses/LICENSE.txt
bagpipes-1.3.4.dist-info/METADATA
bagpipes-1.3.4.dist-info/WHEEL
bagpipes-1.3.4.dist-info/top_level.txt
bagpipes-1.3.4.dist-info/RECORD
