Metadata-Version: 2.4
Name: bagpipes
Version: 1.3.4
Summary: Galaxy spectral fitting
Home-page: https://bagpipes.readthedocs.io
Author: Adam Carnall
Author-email: adamc@roe.ac.uk
Project-URL: readthedocs, https://bagpipes.readthedocs.io
Project-URL: GitHub, https://github.com/ACCarnall/bagpipes
Project-URL: ArXiv, https://arxiv.org/abs/1712.04452
License-File: LICENSE.txt
Requires-Dist: numpy
Requires-Dist: corner
Requires-Dist: pymultinest>=2.11
Requires-Dist: h5py
Requires-Dist: pandas
Requires-Dist: astropy
Requires-Dist: matplotlib>=2.2.2
Requires-Dist: scipy
Requires-Dist: msgpack
Requires-Dist: spectres
Requires-Dist: nautilus-sampler>=1.0.2
Dynamic: author
Dynamic: author-email
Dynamic: description
Dynamic: home-page
Dynamic: license-file
Dynamic: project-url
Dynamic: requires-dist
Dynamic: summary
